crowdtruth/__init__.py
crowdtruth/configuration.py
crowdtruth/crowd_platform.py
crowdtruth/load.py
crowdtruth/run.py
crowdtruth/models/__init__.py
crowdtruth/models/job.py
crowdtruth/models/metrics.py
crowdtruth/models/unit.py
crowdtruth/models/worker.py
crowdtruth_fork-2.1.1.dist-info/LICENSE
crowdtruth_fork-2.1.1.dist-info/METADATA
crowdtruth_fork-2.1.1.dist-info/WHEEL
crowdtruth_fork-2.1.1.dist-info/entry_points.txt
crowdtruth_fork-2.1.1.dist-info/top_level.txt
crowdtruth_fork-2.1.1.dist-info/RECORD
